LICENSE
README.md
setup.py
test/test_api.py
test/test_groups.py
test/test_groups_sync.py
test/test_serialization.py
tlspyo/__init__.py
tlspyo/__main__.py
tlspyo/api.py
tlspyo/client.py
tlspyo/credentials.py
tlspyo/local_protocol_for_client.py
tlspyo/local_protocol_for_server.py
tlspyo/logs.py
tlspyo/server.py
tlspyo/utils.py
tlspyo.egg-info/PKG-INFO
tlspyo.egg-info/SOURCES.txt
tlspyo.egg-info/dependency_links.txt
tlspyo.egg-info/requires.txt
tlspyo.egg-info/top_level.txt