Metadata-Version: 2.1
Name: tlspyo
Version: 0.3.0
Summary: Secure transport of python objects using TLS encryption
Home-page: https://github.com/MISTLab/tls-python-object
Download-URL: https://github.com/MISTLab/tls-python-object/archive/refs/tags/v0.3.0.tar.gz
Author: Yann Bouteiller, Milo Sobral
License: MIT
Keywords: python,tls,ssl,pickle,transfer,object,transport,twisted
Classifier: Development Status :: 4 - Beta
Classifier: Intended Audience :: Developers
Classifier: Intended Audience :: Education
Classifier: Intended Audience :: Information Technology
Classifier: Intended Audience :: Science/Research
Classifier: License :: OSI Approved :: MIT License
Classifier: Operating System :: Microsoft :: Windows
Classifier: Operating System :: POSIX
Classifier: Programming Language :: Python
Classifier: Topic :: Utilities
License-File: LICENSE
